topsis/__init__.py
topsis/__main__.py
Topsis_Rohan_102003029-1.0.0.dist-info/LICENSE
Topsis_Rohan_102003029-1.0.0.dist-info/METADATA
Topsis_Rohan_102003029-1.0.0.dist-info/WHEEL
Topsis_Rohan_102003029-1.0.0.dist-info/entry_points.txt
Topsis_Rohan_102003029-1.0.0.dist-info/top_level.txt
Topsis_Rohan_102003029-1.0.0.dist-info/RECORD
